MANIFEST.in
setup.py
tera.py
terapy/__init__.py
terapy.egg-info/PKG-INFO
terapy.egg-info/SOURCES.txt
terapy.egg-info/dependency_links.txt
terapy.egg-info/entry_points.txt
terapy.egg-info/requires.txt
terapy.egg-info/top_level.txt
terapy/core/__init__.py
terapy/core/axedit.py
terapy/core/button.py
terapy/core/choice.py
terapy/core/dataman.py
terapy/core/dragdrop.py
terapy/core/history.py
terapy/core/menus.py
terapy/core/parsexml.py
terapy/core/plotpanel.py
terapy/core/settings.py
terapy/core/splitter.py
terapy/core/threads.py
terapy/core/tooltip.py
terapy/core/treectrl.py
terapy/core/validator.py
terapy/files/__init__.py
terapy/files/base.py
terapy/files/hdf5.py
terapy/files/origin.py
terapy/files/text.py
terapy/files/xls.py
terapy/filters/__init__.py
terapy/filters/apodization.py
terapy/filters/base.py
terapy/filters/centering.py
terapy/filters/control.py
terapy/filters/ft.py
terapy/filters/harminv.py
terapy/filters/highpass.py
terapy/filters/lombscargle.py
terapy/filters/lowpass.py
terapy/filters/multiply.py
terapy/filters/normalize.py
terapy/filters/offset.py
terapy/filters/power.py
terapy/filters/sgolay.py
terapy/filters/usampling.py
terapy/filters/welch.py
terapy/filters/wldenoise.py
terapy/filters/zeropadding.py
terapy/hardware/__init__.py
terapy/hardware/device.py
terapy/hardware/axes/__init__.py
terapy/hardware/axes/aguc8.py
terapy/hardware/axes/ax_owis.py
terapy/hardware/axes/base.py
terapy/hardware/axes/e3647a.py
terapy/hardware/axes/esp300.py
terapy/hardware/axes/smc100.py
terapy/hardware/input/ADwin_config.py
terapy/hardware/input/__init__.py
terapy/hardware/input/base.py
terapy/hardware/input/hp34401a.py
terapy/hardware/input/inp_adwin.py
terapy/hardware/input/inp_ophir.py
terapy/hardware/input/ophir.py
terapy/hardware/input/pxi5122.py
terapy/hardware/input/pxi5122_config.py
terapy/hardware/input/sr830.py
terapy/icons/__init__.py
terapy/icons/empty.png
terapy/icons/event-display.png
terapy/icons/event-list.png
terapy/icons/event-loop.png
terapy/icons/event-move.png
terapy/icons/event-read.png
terapy/icons/event-reset.png
terapy/icons/event-save.png
terapy/icons/event-scan.png
terapy/icons/event-wait.png
