Metadata-Version: 1.0
Name: terapy
Version: 2.00b6
Summary: Graphical interface for scientific measurements
Home-page: UNKNOWN
Author: Vincent Paeder, Daniel Dietze
Author-email: vincent.paeder@tuwien.ac.at
License: UNKNOWN
Platform: UNKNOWN
